{"iso3":"AZE","name":"Azerbaijan","continent":"Asia","green_km3":3.36,"blue_km3":2.55,"total_km3":5.91,"green_pct":57,"blue_pct":43,"trend_2010_2020_pct":26.2,"area_2020_Mha":0.0,"area_2020_rainfed_Mha":0.0,"area_2020_irrigated_Mha":0.0,"irrigated_share_pct":null,"years":{"2000":{"green_km3":1.61,"blue_km3":1.19,"total_km3":2.81},"2010":{"green_km3":3.03,"blue_km3":1.65,"total_km3":4.68},"2020":{"green_km3":3.36,"blue_km3":2.55,"total_km3":5.91}},"crops":[{"code":"Barley","green_km3":0.95,"blue_km3":0.812,"total_km3":1.763,"green_pct":54,"blue_pct":46},{"code":"Wheat","green_km3":1.231,"blue_km3":0.338,"total_km3":1.569,"green_pct":78,"blue_pct":22},{"code":"Cotton","green_km3":0.216,"blue_km3":0.4,"total_km3":0.616,"green_pct":35,"blue_pct":65},{"code":"TemperateFruit","green_km3":0.428,"blue_km3":0.0,"total_km3":0.428,"green_pct":100,"blue_pct":0},{"code":"OtherCrops","green_km3":0.202,"blue_km3":0.193,"total_km3":0.396,"green_pct":51,"blue_pct":49},{"code":"Potato","green_km3":0.072,"blue_km3":0.243,"total_km3":0.315,"green_pct":23,"blue_pct":77},{"code":"Vegetables","green_km3":0.038,"blue_km3":0.164,"total_km3":0.202,"green_pct":19,"blue_pct":81},{"code":"Maize","green_km3":0.038,"blue_km3":0.146,"total_km3":0.185,"green_pct":21,"blue_pct":79},{"code":"Tomato","green_km3":0.025,"blue_km3":0.097,"total_km3":0.123,"green_pct":21,"blue_pct":79},{"code":"Onion","green_km3":0.03,"blue_km3":0.053,"total_km3":0.082,"green_pct":36,"blue_pct":64},{"code":"OtherOilcrops","green_km3":0.056,"blue_km3":0.0,"total_km3":0.056,"green_pct":100,"blue_pct":0},{"code":"OtherCereals","green_km3":0.004,"blue_km3":0.034,"total_km3":0.038,"green_pct":11,"blue_pct":89},{"code":"Rice","green_km3":0.003,"blue_km3":0.033,"total_km3":0.036,"green_pct":9,"blue_pct":91},{"code":"Sunflower","green_km3":0.032,"blue_km3":0.0,"total_km3":0.032,"green_pct":100,"blue_pct":0},{"code":"Tobacco","green_km3":0.002,"blue_km3":0.018,"total_km3":0.021,"green_pct":12,"blue_pct":88},{"code":"OtherPulses","green_km3":0.019,"blue_km3":0.0,"total_km3":0.019,"green_pct":99,"blue_pct":1},{"code":"SugarBeet","green_km3":0.008,"blue_km3":0.011,"total_km3":0.018,"green_pct":42,"blue_pct":58},{"code":"Tea","green_km3":0.002,"blue_km3":0.006,"total_km3":0.009,"green_pct":28,"blue_pct":72},{"code":"BeansDry","green_km3":0.005,"blue_km3":0.0,"total_km3":0.005,"green_pct":99,"blue_pct":1},{"code":"Lentil","green_km3":0.001,"blue_km3":0.0,"total_km3":0.001,"green_pct":99,"blue_pct":1}]}