{"iso3":"BDI","name":"Burundi","continent":"Africa","green_km3":8.48,"blue_km3":0.48,"total_km3":8.96,"green_pct":95,"blue_pct":5,"trend_2010_2020_pct":23.1,"area_2020_Mha":0.0,"area_2020_rainfed_Mha":0.0,"area_2020_irrigated_Mha":0.0,"irrigated_share_pct":null,"years":{"2000":{"green_km3":5.3,"blue_km3":0.17,"total_km3":5.47},"2010":{"green_km3":6.92,"blue_km3":0.37,"total_km3":7.28},"2020":{"green_km3":8.48,"blue_km3":0.48,"total_km3":8.96}},"crops":[{"code":"BeansDry","green_km3":2.912,"blue_km3":0.0,"total_km3":2.912,"green_pct":100,"blue_pct":0,"area_rainfed_Mha":0.941,"area_irrigated_Mha":0.0,"area_total_Mha":0.941,"yield_rainfed_ton_ha":0.62,"yield_irrigated_ton_ha":null},{"code":"Banana","green_km3":1.512,"blue_km3":0.0,"total_km3":1.512,"green_pct":100,"blue_pct":0,"area_rainfed_Mha":0.159,"area_irrigated_Mha":0.0,"area_total_Mha":0.159,"yield_rainfed_ton_ha":7.82,"yield_irrigated_ton_ha":null},{"code":"Cassava","green_km3":1.312,"blue_km3":0.0,"total_km3":1.312,"green_pct":100,"blue_pct":0,"area_rainfed_Mha":0.307,"area_irrigated_Mha":0.0,"area_total_Mha":0.307,"yield_rainfed_ton_ha":8.0,"yield_irrigated_ton_ha":null},{"code":"Maize","green_km3":0.844,"blue_km3":0.0,"total_km3":0.844,"green_pct":100,"blue_pct":0,"area_rainfed_Mha":0.225,"area_irrigated_Mha":0.0,"area_total_Mha":0.225,"yield_rainfed_ton_ha":1.2,"yield_irrigated_ton_ha":null},{"code":"Rice","green_km3":0.107,"blue_km3":0.389,"total_km3":0.496,"green_pct":22,"blue_pct":78,"area_rainfed_Mha":0.0,"area_irrigated_Mha":0.053,"area_total_Mha":0.053,"yield_rainfed_ton_ha":null,"yield_irrigated_ton_ha":2.49},{"code":"SweetPotato","green_km3":0.385,"blue_km3":0.0,"total_km3":0.385,"green_pct":100,"blue_pct":0,"area_rainfed_Mha":0.081,"area_irrigated_Mha":0.0,"area_total_Mha":0.081,"yield_rainfed_ton_ha":10.86,"yield_irrigated_ton_ha":null},{"code":"TemperateFruit","green_km3":0.215,"blue_km3":0.0,"total_km3":0.215,"green_pct":100,"blue_pct":0,"area_rainfed_Mha":0.025,"area_irrigated_Mha":0.0,"area_total_Mha":0.025,"yield_rainfed_ton_ha":5.12,"yield_irrigated_ton_ha":null},{"code":"Vegetables","green_km3":0.17,"blue_km3":0.033,"total_km3":0.203,"green_pct":84,"blue_pct":16,"area_rainfed_Mha":0.035,"area_irrigated_Mha":0.017,"area_total_Mha":0.052,"yield_rainfed_ton_ha":7.0,"yield_irrigated_ton_ha":13.96},{"code":"ArabicaCoffee","green_km3":0.155,"blue_km3":0.036,"total_km3":0.191,"green_pct":81,"blue_pct":19,"area_rainfed_Mha":0.013,"area_irrigated_Mha":0.005,"area_total_Mha":0.018,"yield_rainfed_ton_ha":null,"yield_irrigated_ton_ha":null},{"code":"Potato","green_km3":0.181,"blue_km3":0.0,"total_km3":0.181,"green_pct":100,"blue_pct":0,"area_rainfed_Mha":0.048,"area_irrigated_Mha":0.0,"area_total_Mha":0.048,"yield_rainfed_ton_ha":8.12,"yield_irrigated_ton_ha":null},{"code":"Sorghum","green_km3":0.107,"blue_km3":0.0,"total_km3":0.107,"green_pct":100,"blue_pct":0,"area_rainfed_Mha":0.034,"area_irrigated_Mha":0.0,"area_total_Mha":0.034,"yield_rainfed_ton_ha":0.57,"yield_irrigated_ton_ha":null},{"code":"Plantain","green_km3":0.103,"blue_km3":0.0,"total_km3":0.103,"green_pct":100,"blue_pct":0,"area_rainfed_Mha":0.011,"area_irrigated_Mha":0.0,"area_total_Mha":0.011,"yield_rainfed_ton_ha":20.63,"yield_irrigated_ton_ha":null},{"code":"Tea","green_km3":0.101,"blue_km3":0.0,"total_km3":0.101,"green_pct":100,"blue_pct":0,"area_rainfed_Mha":0.009,"area_irrigated_Mha":0.0,"area_total_Mha":0.009,"yield_rainfed_ton_ha":5.77,"yield_irrigated_ton_ha":null},{"code":"OtherCereals","green_km3":0.099,"blue_km3":0.0,"total_km3":0.099,"green_pct":100,"blue_pct":0,"area_rainfed_Mha":0.019,"area_irrigated_Mha":0.0,"area_total_Mha":0.019,"yield_rainfed_ton_ha":0.6,"yield_irrigated_ton_ha":null},{"code":"OilPalm","green_km3":0.082,"blue_km3":0.0,"total_km3":0.082,"green_pct":100,"blue_pct":0,"area_rainfed_Mha":0.009,"area_irrigated_Mha":0.0,"area_total_Mha":0.009,"yield_rainfed_ton_ha":9.81,"yield_irrigated_ton_ha":null},{"code":"Groundnut","green_km3":0.059,"blue_km3":0.0,"total_km3":0.059,"green_pct":100,"blue_pct":0,"area_rainfed_Mha":0.016,"area_irrigated_Mha":0.0,"area_total_Mha":0.016,"yield_rainfed_ton_ha":0.61,"yield_irrigated_ton_ha":null},{"code":"Wheat","green_km3":0.045,"blue_km3":0.0,"total_km3":0.045,"green_pct":100,"blue_pct":0,"area_rainfed_Mha":0.011,"area_irrigated_Mha":0.0,"area_total_Mha":0.011,"yield_rainfed_ton_ha":0.7,"yield_irrigated_ton_ha":null},{"code":"Sugarcane","green_km3":0.019,"blue_km3":0.023,"total_km3":0.041,"green_pct":45,"blue_pct":55,"area_rainfed_Mha":0.0,"area_irrigated_Mha":0.003,"area_total_Mha":0.003,"yield_rainfed_ton_ha":null,"yield_irrigated_ton_ha":67.56},{"code":"SmallMillet","green_km3":0.036,"blue_km3":0.0,"total_km3":0.036,"green_pct":100,"blue_pct":0,"area_rainfed_Mha":0.01,"area_irrigated_Mha":0.0,"area_total_Mha":0.01,"yield_rainfed_ton_ha":null,"yield_irrigated_ton_ha":null},{"code":"OtherRoots","green_km3":0.016,"blue_km3":0.0,"total_km3":0.016,"green_pct":100,"blue_pct":0,"area_rainfed_Mha":0.006,"area_irrigated_Mha":0.0,"area_total_Mha":0.006,"yield_rainfed_ton_ha":23.32,"yield_irrigated_ton_ha":null},{"code":"OtherPulses","green_km3":0.009,"blue_km3":0.0,"total_km3":0.009,"green_pct":100,"blue_pct":0,"area_rainfed_Mha":0.003,"area_irrigated_Mha":0.0,"area_total_Mha":0.003,"yield_rainfed_ton_ha":4.32,"yield_irrigated_ton_ha":null},{"code":"Tobacco","green_km3":0.005,"blue_km3":0.0,"total_km3":0.005,"green_pct":100,"blue_pct":0,"area_rainfed_Mha":0.002,"area_irrigated_Mha":0.0,"area_total_Mha":0.002,"yield_rainfed_ton_ha":0.86,"yield_irrigated_ton_ha":null},{"code":"Pigeonpea","green_km3":0.003,"blue_km3":0.0,"total_km3":0.003,"green_pct":100,"blue_pct":0,"area_rainfed_Mha":0.003,"area_irrigated_Mha":0.0,"area_total_Mha":0.003,"yield_rainfed_ton_ha":1.15,"yield_irrigated_ton_ha":null},{"code":"Yams","green_km3":0.001,"blue_km3":0.0,"total_km3":0.001,"green_pct":100,"blue_pct":0,"area_rainfed_Mha":0.0,"area_irrigated_Mha":0.0,"area_total_Mha":0.0,"yield_rainfed_ton_ha":9.18,"yield_irrigated_ton_ha":null}]}