{"iso3":"BGR","name":"Bulgaria","continent":"Europe","green_km3":9.19,"blue_km3":0.41,"total_km3":9.59,"green_pct":96,"blue_pct":4,"trend_2010_2020_pct":4.8,"area_2020_Mha":0.0,"area_2020_rainfed_Mha":0.0,"area_2020_irrigated_Mha":0.0,"irrigated_share_pct":null,"years":{"2000":{"green_km3":8.38,"blue_km3":0.88,"total_km3":9.26},"2010":{"green_km3":8.84,"blue_km3":0.31,"total_km3":9.15},"2020":{"green_km3":9.19,"blue_km3":0.41,"total_km3":9.59}},"crops":[{"code":"Wheat","green_km3":4.251,"blue_km3":0.0,"total_km3":4.251,"green_pct":100,"blue_pct":0},{"code":"Sunflower","green_km3":2.205,"blue_km3":0.044,"total_km3":2.248,"green_pct":98,"blue_pct":2},{"code":"Maize","green_km3":1.451,"blue_km3":0.166,"total_km3":1.617,"green_pct":90,"blue_pct":10},{"code":"Rapeseed","green_km3":0.379,"blue_km3":0.0,"total_km3":0.379,"green_pct":100,"blue_pct":0},{"code":"TemperateFruit","green_km3":0.283,"blue_km3":0.0,"total_km3":0.283,"green_pct":100,"blue_pct":0},{"code":"Barley","green_km3":0.231,"blue_km3":0.0,"total_km3":0.231,"green_pct":100,"blue_pct":0},{"code":"OtherCereals","green_km3":0.14,"blue_km3":0.0,"total_km3":0.14,"green_pct":100,"blue_pct":0},{"code":"Rice","green_km3":0.023,"blue_km3":0.085,"total_km3":0.108,"green_pct":22,"blue_pct":78},{"code":"OtherPulses","green_km3":0.056,"blue_km3":0.041,"total_km3":0.097,"green_pct":58,"blue_pct":42},{"code":"OtherCrops","green_km3":0.042,"blue_km3":0.003,"total_km3":0.045,"green_pct":94,"blue_pct":6},{"code":"Vegetables","green_km3":0.02,"blue_km3":0.024,"total_km3":0.044,"green_pct":46,"blue_pct":54},{"code":"Potato","green_km3":0.027,"blue_km3":0.011,"total_km3":0.038,"green_pct":71,"blue_pct":29},{"code":"OtherOilcrops","green_km3":0.025,"blue_km3":0.0,"total_km3":0.025,"green_pct":100,"blue_pct":0},{"code":"Cotton","green_km3":0.008,"blue_km3":0.016,"total_km3":0.024,"green_pct":32,"blue_pct":68},{"code":"Tomato","green_km3":0.008,"blue_km3":0.009,"total_km3":0.017,"green_pct":46,"blue_pct":54},{"code":"Onion","green_km3":0.007,"blue_km3":0.005,"total_km3":0.013,"green_pct":58,"blue_pct":42},{"code":"Soybean","green_km3":0.01,"blue_km3":0.001,"total_km3":0.011,"green_pct":90,"blue_pct":10},{"code":"Sorghum","green_km3":0.01,"blue_km3":0.0,"total_km3":0.01,"green_pct":100,"blue_pct":0},{"code":"Tobacco","green_km3":0.008,"blue_km3":0.001,"total_km3":0.009,"green_pct":88,"blue_pct":12},{"code":"OtherFibres","green_km3":0.002,"blue_km3":0.003,"total_km3":0.004,"green_pct":39,"blue_pct":61}]}